prompt_db_web/__init__.py
prompt_db_web/prompt_db_web.py
prompt_db_web-0.1.1.dist-info/METADATA
prompt_db_web-0.1.1.dist-info/WHEEL
prompt_db_web-0.1.1.dist-info/RECORD
